{
  "split": "new",
  "image_filename": "CLEVR_new_000000.png",
  "objects": [
    {
      "pixel_coords": [
        101,
        122,
        9.640990257263184
      ],
      "size": "large",
      "color": "gray",
      "3d_coords": [
        0.012304676696658134,
        -2.224102020263672,
        0.699999988079071
      ],
      "material": "rubber",
      "rotation": 317.89422454803935,
      "shape": "sphere"
    },
    {
      "pixel_coords": [
        149,
        95,
        12.272287368774414
      ],
      "size": "small",
      "color": "yellow",
      "3d_coords": [
        -1.1914976835250854,
        0.5758709907531738,
        0.3499999940395355
      ],
      "material": "rubber",
      "rotation": 262.64320034258446,
      "shape": "cube"
    },
    {
      "pixel_coords": [
        122,
        156,
        8.750055313110352
      ],
      "size": "small",
      "color": "brown",
      "3d_coords": [
        1.3445532321929932,
        -2.5114586353302,
        0.3499999940395355
      ],
      "material": "rubber",
      "rotation": 194.42787851639613,
      "shape": "sphere"
    },
    {
      "pixel_coords": [
        38,
        97,
        11.227058410644531
      ],
      "size": "large",
      "color": "brown",
      "3d_coords": [
        -2.84761381149292,
        -2.7206742763519287,
        0.699999988079071
      ],
      "material": "rubber",
      "rotation": 332.7295629354999,
      "shape": "cube"
    },
    {
      "pixel_coords": [
        192,
        146,
        9.18127727508545
      ],
      "size": "small",
      "color": "blue",
      "3d_coords": [
        2.19948148727417,
        -0.8535068035125732,
        0.3499999940395355
      ],
      "material": "metal",
      "rotation": 269.4511762276586,
      "shape": "cylinder"
    },
    {
      "pixel_coords": [
        206,
        75,
        13.033376693725586
      ],
      "size": "large",
      "color": "gray",
      "3d_coords": [
        -0.5478609800338745,
        2.816850423812866,
        0.699999988079071
      ],
      "material": "metal",
      "rotation": 221.8024267537745,
      "shape": "cube"
    },
    {
      "pixel_coords": [
        237,
        113,
        10.135536193847656
      ],
      "size": "large",
      "color": "green",
      "3d_coords": [
        2.196288824081421,
        0.9991342425346375,
        0.699999988079071
      ],
      "material": "metal",
      "rotation": 262.5335610921236,
      "shape": "cylinder"
    },
    {
      "pixel_coords": [
        286,
        113,
        10.93325424194336
      ],
      "size": "small",
      "color": "gray",
      "3d_coords": [
        2.8278582096099854,
        2.757739543914795,
        0.3499999940395355
      ],
      "material": "metal",
      "rotation": 207.14342841241682,
      "shape": "sphere"
    },
    {
      "pixel_coords": [
        244,
        89,
        11.80341911315918
      ],
      "size": "large",
      "color": "gray",
      "3d_coords": [
        1.2217369079589844,
        2.7096729278564453,
        0.699999988079071
      ],
      "material": "rubber",
      "rotation": 305.552091344415,
      "shape": "cylinder"
    },
    {
      "pixel_coords": [
        178,
        168,
        7.698759078979492
      ],
      "size": "large",
      "color": "yellow",
      "3d_coords": [
        2.986121654510498,
        -2.1962709426879883,
        0.699999988079071
      ],
      "material": "rubber",
      "rotation": 32.47217363912978,
      "shape": "sphere"
    }
  ],
  "relationships": {
    "left": [
      [
        3
      ],
      [
        0,
        2,
        3
      ],
      [
        0,
        3
      ],
      [],
      [
        0,
        1,
        2,
        3,
        9
      ],
      [
        0,
        1,
        2,
        3,
        4,
        9
      ],
      [
        0,
        1,
        2,
        3,
        4,
        5,
        9
      ],
      [
        0,
        1,
        2,
        3,
        4,
        5,
        6,
        8,
        9
      ],
      [
        0,
        1,
        2,
        3,
        4,
        5,
        6,
        9
      ],
      [
        0,
        1,
        2,
        3
      ]
    ],
    "right": [
      [
        1,
        2,
        4,
        5,
        6,
        7,
        8,
        9
      ],
      [
        4,
        5,
        6,
        7,
        8,
        9
      ],
      [
        1,
        4,
        5,
        6,
        7,
        8,
        9
      ],
      [
        0,
        1,
        2,
        4,
        5,
        6,
        7,
        8,
        9
      ],
      [
        5,
        6,
        7,
        8
      ],
      [
        6,
        7,
        8
      ],
      [
        7,
        8
      ],
      [],
      [
        7
      ],
      [
        4,
        5,
        6,
        7,
        8
      ]
    ],
    "front": [
      [
        2,
        4,
        9
      ],
      [
        0,
        2,
        3,
        4,
        6,
        7,
        8,
        9
      ],
      [
        9
      ],
      [
        0,
        2,
        4,
        6,
        7,
        9
      ],
      [
        2,
        9
      ],
      [
        0,
        1,
        2,
        3,
        4,
        6,
        7,
        8,
        9
      ],
      [
        0,
        2,
        4,
        9
      ],
      [
        0,
        2,
        4,
        6,
        9
      ],
      [
        0,
        2,
        3,
        4,
        6,
        7,
        9
      ],
      []
    ],
    "behind": [
      [
        1,
        3,
        5,
        6,
        7,
        8
      ],
      [
        5
      ],
      [
        0,
        1,
        3,
        4,
        5,
        6,
        7,
        8
      ],
      [
        1,
        5,
        8
      ],
      [
        0,
        1,
        3,
        5,
        6,
        7,
        8
      ],
      [],
      [
        1,
        3,
        5,
        7,
        8
      ],
      [
        1,
        3,
        5,
        8
      ],
      [
        1,
        5
      ],
      [
        0,
        1,
        2,
        3,
        4,
        5,
        6,
        7,
        8
      ]
    ]
  },
  "image_index": 0,
  "directions": {
    "above": [
      0.0,
      0.0,
      1.0
    ],
    "front": [
      0.754490315914154,
      -0.6563112735748291,
      -0.0
    ],
    "behind": [
      -0.754490315914154,
      0.6563112735748291,
      0.0
    ],
    "below": [
      -0.0,
      -0.0,
      -1.0
    ],
    "left": [
      -0.6563112735748291,
      -0.7544902563095093,
      0.0
    ],
    "right": [
      0.6563112735748291,
      0.7544902563095093,
      -0.0
    ]
  }
}